revolt_mpd_status/__init__.py
revolt_mpd_status-0.0.2.dist-info/METADATA
revolt_mpd_status-0.0.2.dist-info/WHEEL
revolt_mpd_status-0.0.2.dist-info/entry_points.txt
revolt_mpd_status-0.0.2.dist-info/licenses/LICENSE
revolt_mpd_status-0.0.2.dist-info/RECORD
