Metadata-Version: 2.3
Name: revolt_mpd_status
Version: 0.0.2
Summary: Show friends what you are listening on MPD
Project-URL: Homepage, https://github.com/amycatgirl/mpdrevoltstatus
Project-URL: Issues, https://github.com/amycatgirl/mpdrevoltstatus/issues
Author-email: Amy Pérez <amy+heya@amogus.cloud>
License: Copyright (c) 2024 Amy Pérez
License-File: LICENSE
Classifier: License :: OSI Approved :: MIT License
Classifier: Operating System :: OS Independent
Classifier: Programming Language :: Python :: 3
Requires-Python: >=3.8
Requires-Dist: docopt-ng~=0.9.0
Requires-Dist: python-mpd2~=3.1.1
Requires-Dist: revolt-py~=0.2.0
